{
	"song": {
		"player1": "PLAYABLE_JASMINU22",
		"player2": "nclol",
		"events": [],
		"notes": [
			{
				"sectionNotes": [],
				"sectionBeats": 4,
				"gfSection": false,
				"altAnim": false,
				"bpm": 150,
				"changeBPM": false,
				"mustHitSection": true
			},
			{
				"sectionNotes": [],
				"sectionBeats": 4,
				"gfSection": false,
				"altAnim": false,
				"bpm": 150,
				"changeBPM": false,
				"mustHitSection": true
			},
			{
				"sectionNotes": [],
				"sectionBeats": 4,
				"gfSection": false,
				"altAnim": false,
				"bpm": 150,
				"changeBPM": false,
				"mustHitSection": true
			},
			{
				"sectionNotes": [
					[
						7200,
						6,
						0
					]
				],
				"sectionBeats": 4,
				"gfSection": false,
				"altAnim": false,
				"bpm": 150,
				"changeBPM": false,
				"mustHitSection": true
			},
			{
				"sectionNotes": [
					[
						9600,
						0,
						0
					],
					[
						9900,
						1,
						0
					],
					[
						10050,
						1,
						0
					],
					[
						10200,
						0,
						0
					],
					[
						10500,
						1,
						0
					],
					[
						10800,
						3,
						0
					],
					[
						11100,
						1,
						0
					],
					[
						11400,
						2,
						0
					],
					[
						11700,
						1,
						0
					]
				],
				"sectionBeats": 4,
				"gfSection": false,
				"altAnim": false,
				"bpm": 150,
				"changeBPM": false,
				"mustHitSection": true
			},
			{
				"sectionNotes": [
					[
						12000,
						0,
						450
					],
					[
						12600,
						1,
						450
					],
					[
						13500,
						1,
						0
					],
					[
						13800,
						2,
						0
					],
					[
						14100,
						3,
						0
					]
				],
				"sectionBeats": 4,
				"gfSection": false,
				"altAnim": false,
				"bpm": 150,
				"changeBPM": false,
				"mustHitSection": true
			},
			{
				"sectionNotes": [
					[
						14400,
						2,
						0
					],
					[
						14700,
						0,
						0
					],
					[
						15000,
						3,
						0
					],
					[
						15300,
						1,
						0
					],
					[
						16200,
						1,
						450
					],
					[
						15600,
						2,
						450
					]
				],
				"sectionBeats": 4,
				"gfSection": false,
				"altAnim": false,
				"bpm": 150,
				"changeBPM": false,
				"mustHitSection": true
			},
			{
				"sectionNotes": [
					[
						16800,
						2,
						900
					],
					[
						18300,
						2,
						0
					],
					[
						18600,
						1,
						0
					],
					[
						18900,
						2,
						0
					]
				],
				"sectionBeats": 4,
				"gfSection": false,
				"altAnim": false,
				"bpm": 150,
				"changeBPM": false,
				"mustHitSection": true
			},
			{
				"sectionNotes": [
					[
						19200,
						0,
						0
					],
					[
						19500,
						1,
						0
					],
					[
						19800,
						3,
						0
					],
					[
						20100,
						2,
						0
					],
					[
						20400,
						3,
						0
					],
					[
						20700,
						2,
						0
					],
					[
						21000,
						0,
						0
					],
					[
						21300,
						3,
						0
					]
				],
				"sectionBeats": 4,
				"gfSection": false,
				"altAnim": false,
				"bpm": 150,
				"changeBPM": false,
				"mustHitSection": true
			},
			{
				"sectionNotes": [
					[
						21600,
						1,
						0
					],
					[
						21900,
						2,
						0
					],
					[
						22200,
						1,
						0
					],
					[
						23100,
						3,
						0
					],
					[
						23400,
						2,
						0
					],
					[
						23700,
						0,
						0
					],
					[
						22500,
						3,
						225
					]
				],
				"sectionBeats": 4,
				"gfSection": false,
				"altAnim": false,
				"bpm": 150,
				"changeBPM": false,
				"mustHitSection": true
			},
			{
				"sectionNotes": [
					[
						24000,
						0,
						0
					],
					[
						24300,
						1,
						0
					],
					[
						24600,
						0,
						0
					],
					[
						24900,
						2,
						0
					],
					[
						25200,
						1,
						0
					],
					[
						25500,
						3,
						0
					],
					[
						25800,
						2,
						0
					],
					[
						26100,
						1,
						0
					]
				],
				"sectionBeats": 4,
				"gfSection": false,
				"altAnim": false,
				"bpm": 150,
				"changeBPM": false,
				"mustHitSection": true
			},
			{
				"sectionNotes": [
					[
						27000,
						1,
						525
					],
					[
						26400,
						2,
						450
					],
					[
						27900,
						2,
						0
					],
					[
						28200,
						1,
						0
					],
					[
						28500,
						2,
						0
					]
				],
				"sectionBeats": 4,
				"gfSection": false,
				"altAnim": false,
				"bpm": 150,
				"changeBPM": false,
				"mustHitSection": true
			},
			{
				"sectionNotes": [
					[
						28800,
						0,
						0
					],
					[
						29100,
						1,
						0
					],
					[
						29400,
						0,
						0
					],
					[
						29700,
						3,
						0
					],
					[
						30000,
						2,
						450
					],
					[
						30600,
						3,
						450
					]
				],
				"sectionBeats": 4,
				"gfSection": false,
				"altAnim": false,
				"bpm": 150,
				"changeBPM": false,
				"mustHitSection": true
			},
			{
				"sectionNotes": [
					[
						31200,
						0,
						0
					],
					[
						31500,
						1,
						0
					],
					[
						31800,
						3,
						0
					],
					[
						32100,
						2,
						375
					],
					[
						32700,
						1,
						0
					],
					[
						33000,
						0,
						0
					],
					[
						33300,
						1,
						0
					]
				],
				"sectionBeats": 4,
				"gfSection": false,
				"altAnim": false,
				"bpm": 150,
				"changeBPM": false,
				"mustHitSection": true
			},
			{
				"sectionNotes": [
					[
						33600,
						2,
						0
					],
					[
						33900,
						1,
						0
					],
					[
						34200,
						2,
						0
					],
					[
						34500,
						0,
						0
					],
					[
						34800,
						3,
						0
					],
					[
						35100,
						1,
						0
					],
					[
						35400,
						3,
						0
					],
					[
						35700,
						2,
						0
					]
				],
				"sectionBeats": 4,
				"gfSection": false,
				"altAnim": false,
				"bpm": 150,
				"changeBPM": false,
				"mustHitSection": true
			},
			{
				"sectionNotes": [
					[
						36000,
						1,
						2250
					]
				],
				"sectionBeats": 4,
				"gfSection": false,
				"altAnim": false,
				"bpm": 150,
				"changeBPM": false,
				"mustHitSection": true
			},
			{
				"sectionNotes": [
					[
						39900,
						2,
						0
					],
					[
						40200,
						1,
						0
					],
					[
						40500,
						2,
						0
					]
				],
				"sectionBeats": 4,
				"gfSection": false,
				"altAnim": false,
				"bpm": 150,
				"changeBPM": false,
				"mustHitSection": true
			},
			{
				"sectionNotes": [
					[
						40800,
						0,
						0
					],
					[
						41100,
						1,
						0
					],
					[
						41400,
						0,
						0
					],
					[
						41700,
						3,
						0
					],
					[
						42000,
						2,
						1050
					]
				],
				"sectionBeats": 4,
				"gfSection": false,
				"altAnim": false,
				"bpm": 150,
				"changeBPM": false,
				"mustHitSection": true
			},
			{
				"sectionNotes": [
					[
						43200,
						3,
						0
					],
					[
						43500,
						0,
						0
					],
					[
						43800,
						1,
						0
					],
					[
						44100,
						2,
						0
					],
					[
						44400,
						1,
						450
					],
					[
						45000,
						0,
						375
					]
				],
				"sectionBeats": 4,
				"gfSection": false,
				"altAnim": false,
				"bpm": 150,
				"changeBPM": false,
				"mustHitSection": true
			},
			{
				"sectionNotes": [
					[
						45600,
						3,
						0
					],
					[
						46500,
						2,
						0
					],
					[
						46800,
						1,
						450
					],
					[
						45900,
						2,
						0
					],
					[
						46200,
						0,
						0
					],
					[
						47400,
						3,
						300
					],
					[
						47850,
						2,
						0
					],
					[
						47925,
						1,
						0
					]
				],
				"sectionBeats": 4,
				"gfSection": false,
				"altAnim": false,
				"bpm": 150,
				"changeBPM": false,
				"mustHitSection": true
			},
			{
				"sectionNotes": [
					[
						48000,
						0,
						0
					],
					[
						48300,
						2,
						1950
					]
				],
				"sectionBeats": 4,
				"gfSection": false,
				"altAnim": false,
				"bpm": 150,
				"changeBPM": false,
				"mustHitSection": true
			},
			{
				"sectionNotes": [],
				"sectionBeats": 4,
				"gfSection": false,
				"altAnim": false,
				"bpm": 150,
				"changeBPM": false,
				"mustHitSection": true
			},
			{
				"sectionNotes": [],
				"sectionBeats": 4,
				"gfSection": false,
				"altAnim": false,
				"bpm": 150,
				"changeBPM": false,
				"mustHitSection": true
			},
			{
				"sectionNotes": [],
				"sectionBeats": 4,
				"gfSection": false,
				"altAnim": false,
				"bpm": 150,
				"changeBPM": false,
				"mustHitSection": true
			},
			{
				"sectionNotes": [],
				"sectionBeats": 4,
				"gfSection": false,
				"altAnim": false,
				"bpm": 150,
				"changeBPM": false,
				"mustHitSection": true
			},
			{
				"sectionNotes": [],
				"sectionBeats": 4,
				"gfSection": false,
				"altAnim": false,
				"bpm": 150,
				"changeBPM": false,
				"mustHitSection": true
			},
			{
				"sectionNotes": [],
				"sectionBeats": 4,
				"gfSection": false,
				"altAnim": false,
				"bpm": 150,
				"changeBPM": false,
				"mustHitSection": true
			},
			{
				"sectionNotes": [],
				"sectionBeats": 4,
				"gfSection": false,
				"altAnim": false,
				"bpm": 150,
				"changeBPM": false,
				"mustHitSection": true
			},
			{
				"sectionNotes": [],
				"sectionBeats": 4,
				"gfSection": false,
				"altAnim": false,
				"bpm": 150,
				"changeBPM": false,
				"mustHitSection": true
			},
			{
				"sectionNotes": [],
				"sectionBeats": 4,
				"gfSection": false,
				"altAnim": false,
				"bpm": 150,
				"changeBPM": false,
				"mustHitSection": true
			},
			{
				"sectionNotes": [],
				"sectionBeats": 4,
				"gfSection": false,
				"altAnim": false,
				"bpm": 150,
				"changeBPM": false,
				"mustHitSection": true
			},
			{
				"sectionNotes": [],
				"sectionBeats": 4,
				"gfSection": false,
				"altAnim": false,
				"bpm": 150,
				"changeBPM": false,
				"mustHitSection": true
			},
			{
				"sectionNotes": [],
				"sectionBeats": 4,
				"gfSection": false,
				"altAnim": false,
				"bpm": 150,
				"changeBPM": false,
				"mustHitSection": true
			},
			{
				"sectionNotes": [],
				"sectionBeats": 4,
				"gfSection": false,
				"altAnim": false,
				"bpm": 150,
				"changeBPM": false,
				"mustHitSection": true
			},
			{
				"sectionNotes": [],
				"sectionBeats": 4,
				"gfSection": false,
				"altAnim": false,
				"bpm": 150,
				"changeBPM": false,
				"mustHitSection": true
			},
			{
				"sectionNotes": [],
				"sectionBeats": 4,
				"gfSection": false,
				"altAnim": false,
				"bpm": 150,
				"changeBPM": false,
				"mustHitSection": true
			},
			{
				"sectionNotes": [],
				"sectionBeats": 4,
				"gfSection": false,
				"altAnim": false,
				"bpm": 150,
				"changeBPM": false,
				"mustHitSection": true
			},
			{
				"sectionNotes": [],
				"sectionBeats": 4,
				"gfSection": false,
				"altAnim": false,
				"bpm": 150,
				"changeBPM": false,
				"mustHitSection": true
			},
			{
				"sectionNotes": [],
				"sectionBeats": 4,
				"gfSection": false,
				"altAnim": false,
				"bpm": 150,
				"changeBPM": false,
				"mustHitSection": true
			},
			{
				"sectionNotes": [],
				"sectionBeats": 4,
				"gfSection": false,
				"altAnim": false,
				"bpm": 150,
				"changeBPM": false,
				"mustHitSection": true
			},
			{
				"sectionNotes": [],
				"sectionBeats": 4,
				"gfSection": false,
				"altAnim": false,
				"bpm": 150,
				"changeBPM": false,
				"mustHitSection": true
			},
			{
				"sectionNotes": [],
				"sectionBeats": 4,
				"gfSection": false,
				"altAnim": false,
				"bpm": 150,
				"changeBPM": false,
				"mustHitSection": true
			},
			{
				"sectionNotes": [],
				"sectionBeats": 4,
				"gfSection": false,
				"altAnim": false,
				"bpm": 150,
				"changeBPM": false,
				"mustHitSection": true
			},
			{
				"sectionNotes": [],
				"sectionBeats": 4,
				"gfSection": false,
				"altAnim": false,
				"bpm": 150,
				"changeBPM": false,
				"mustHitSection": true
			},
			{
				"sectionNotes": [],
				"sectionBeats": 4,
				"gfSection": false,
				"altAnim": false,
				"bpm": 150,
				"changeBPM": false,
				"mustHitSection": true
			},
			{
				"sectionNotes": [],
				"sectionBeats": 4,
				"gfSection": false,
				"altAnim": false,
				"bpm": 150,
				"changeBPM": false,
				"mustHitSection": true
			},
			{
				"sectionNotes": [],
				"sectionBeats": 4,
				"gfSection": false,
				"altAnim": false,
				"bpm": 150,
				"changeBPM": false,
				"mustHitSection": true
			},
			{
				"sectionNotes": [],
				"sectionBeats": 4,
				"gfSection": false,
				"altAnim": false,
				"bpm": 150,
				"changeBPM": false,
				"mustHitSection": true
			},
			{
				"sectionNotes": [],
				"sectionBeats": 4,
				"gfSection": false,
				"altAnim": false,
				"bpm": 150,
				"changeBPM": false,
				"mustHitSection": true
			},
			{
				"sectionNotes": [],
				"sectionBeats": 4,
				"gfSection": false,
				"altAnim": false,
				"bpm": 150,
				"changeBPM": false,
				"mustHitSection": true
			},
			{
				"sectionNotes": [],
				"sectionBeats": 4,
				"gfSection": false,
				"altAnim": false,
				"bpm": 150,
				"changeBPM": false,
				"mustHitSection": true
			},
			{
				"sectionNotes": [],
				"sectionBeats": 4,
				"gfSection": false,
				"altAnim": false,
				"bpm": 150,
				"changeBPM": false,
				"mustHitSection": true
			},
			{
				"sectionNotes": [],
				"sectionBeats": 4,
				"gfSection": false,
				"altAnim": false,
				"bpm": 150,
				"changeBPM": false,
				"mustHitSection": true
			},
			{
				"sectionNotes": [],
				"sectionBeats": 4,
				"gfSection": false,
				"altAnim": false,
				"bpm": 150,
				"changeBPM": false,
				"mustHitSection": true
			},
			{
				"sectionNotes": [],
				"sectionBeats": 4,
				"gfSection": false,
				"altAnim": false,
				"bpm": 150,
				"changeBPM": false,
				"mustHitSection": true
			},
			{
				"sectionNotes": [],
				"sectionBeats": 4,
				"gfSection": false,
				"altAnim": false,
				"bpm": 150,
				"changeBPM": false,
				"mustHitSection": true
			},
			{
				"sectionNotes": [],
				"sectionBeats": 4,
				"gfSection": false,
				"altAnim": false,
				"bpm": 150,
				"changeBPM": false,
				"mustHitSection": true
			},
			{
				"sectionNotes": [],
				"sectionBeats": 4,
				"gfSection": false,
				"altAnim": false,
				"bpm": 150,
				"changeBPM": false,
				"mustHitSection": true
			},
			{
				"sectionNotes": [],
				"sectionBeats": 4,
				"gfSection": false,
				"altAnim": false,
				"bpm": 150,
				"changeBPM": false,
				"mustHitSection": true
			},
			{
				"sectionNotes": [],
				"sectionBeats": 4,
				"gfSection": false,
				"altAnim": false,
				"bpm": 150,
				"changeBPM": false,
				"mustHitSection": true
			},
			{
				"sectionNotes": [],
				"sectionBeats": 4,
				"gfSection": false,
				"altAnim": false,
				"bpm": 150,
				"changeBPM": false,
				"mustHitSection": true
			},
			{
				"sectionNotes": [],
				"sectionBeats": 4,
				"gfSection": false,
				"altAnim": false,
				"bpm": 150,
				"changeBPM": false,
				"mustHitSection": true
			},
			{
				"sectionNotes": [],
				"sectionBeats": 4,
				"gfSection": false,
				"altAnim": false,
				"bpm": 150,
				"changeBPM": false,
				"mustHitSection": true
			},
			{
				"sectionNotes": [],
				"sectionBeats": 4,
				"gfSection": false,
				"altAnim": false,
				"bpm": 150,
				"changeBPM": false,
				"mustHitSection": true
			},
			{
				"sectionNotes": [],
				"sectionBeats": 4,
				"gfSection": false,
				"altAnim": false,
				"bpm": 150,
				"changeBPM": false,
				"mustHitSection": true
			},
			{
				"sectionNotes": [],
				"sectionBeats": 4,
				"gfSection": false,
				"altAnim": false,
				"bpm": 150,
				"changeBPM": false,
				"mustHitSection": true
			}
		],
		"gfVersion": "speakers",
		"song": "purple-girl",
		"needsVoices": true,
		"stage": "carnaval",
		"bpm": 100,
		"speed": 2.4
	}
}